{
  "file": "src/test_reflect.py",
  "method": "src.test_reflect.apply_reflect_padding#1",
  "blocks": [
    {
      "id": 1,
      "name": "step 1",
      "method": "src.test_reflect.apply_reflect_padding#1",
      "cstart": -1,
      "cend": -1,
      "tstart": -1,
      "tend": -1
    },
    {
      "id": 2,
      "name": "step 2",
      "method": "src.test_reflect.apply_reflect_padding#1",
      "cstart": 53,
      "cend": 53,
      "tstart": -1,
      "tend": -1
    },
    {
      "id": 3,
      "name": "step 3",
      "method": "src.test_reflect.apply_reflect_padding#1",
      "cstart": 72,
      "cend": 72,
      "tstart": -1,
      "tend": -1
    },
    {
      "id": 4,
      "name": "step 4",
      "method": "src.test_reflect.apply_reflect_padding#1",
      "cstart": 73,
      "cend": 73,
      "tstart": 1,
      "tend": 1
    },
    {
      "id": 5,
      "name": "step 5",
      "method": "src.test_reflect.apply_reflect_padding#1",
      "cstart": 53,
      "cend": 53,
      "tstart": -1,
      "tend": -1
    },
    {
      "id": 6,
      "name": "step 6",
      "method": "src.test_reflect.apply_reflect_padding#1",
      "cstart": 60,
      "cend": 60,
      "tstart": 2,
      "tend": 2
    },
    {
      "id": 7,
      "name": "step 7",
      "method": "src.test_reflect.apply_reflect_padding#1",
      "cstart": 61,
      "cend": 61,
      "tstart": 3,
      "tend": 3
    },
    {
      "id": 8,
      "name": "step 8",
      "method": "src.test_reflect.apply_reflect_padding#1",
      "cstart": 1,
      "cend": 1,
      "tstart": -1,
      "tend": -1
    },
    {
      "id": 9,
      "name": "step 9",
      "method": "src.test_reflect.apply_reflect_padding#1",
      "cstart": 2,
      "cend": 2,
      "tstart": 4,
      "tend": 4
    },
    {
      "id": 10,
      "name": "step 10",
      "method": "src.test_reflect.apply_reflect_padding#1",
      "cstart": 3,
      "cend": 3,
      "tstart": 5,
      "tend": 5
    },
    {
      "id": 11,
      "name": "step 11",
      "method": "src.test_reflect.apply_reflect_padding#1",
      "cstart": 4,
      "cend": 4,
      "tstart": 6,
      "tend": 6
    },
    {
      "id": 12,
      "name": "step 12",
      "method": "src.test_reflect.apply_reflect_padding#1",
      "cstart": 5,
      "cend": 5,
      "tstart": 7,
      "tend": 7
    },
    {
      "id": 13,
      "name": "step 13",
      "method": "src.test_reflect.apply_reflect_padding#1",
      "cstart": 7,
      "cend": 7,
      "tstart": 8,
      "tend": 8
    },
    {
      "id": 14,
      "name": "step 14",
      "method": "src.test_reflect.apply_reflect_padding#1",
      "cstart": 8,
      "cend": 8,
      "tstart": 9,
      "tend": 9
    },
    {
      "id": 15,
      "name": "step 15",
      "method": "src.test_reflect.apply_reflect_padding#1",
      "cstart": 10,
      "cend": 10,
      "tstart": 10,
      "tend": 10
    },
    {
      "id": 16,
      "name": "step 16",
      "method": "src.test_reflect.apply_reflect_padding#1",
      "cstart": 13,
      "cend": 13,
      "tstart": 11,
      "tend": 11
    },
    {
      "id": 17,
      "name": "step 17",
      "method": "src.test_reflect.apply_reflect_padding#1",
      "cstart": 13,
      "cend": 13,
      "tstart": 12,
      "tend": 12
    },
    {
      "id": 18,
      "name": "step 18",
      "method": "src.test_reflect.apply_reflect_padding#1",
      "cstart": 13,
      "cend": 13,
      "tstart": 13,
      "tend": 13
    },
    {
      "id": 19,
      "name": "step 19",
      "method": "src.test_reflect.apply_reflect_padding#1",
      "cstart": 13,
      "cend": 13,
      "tstart": 14,
      "tend": 14
    },
    {
      "id": 20,
      "name": "step 20",
      "method": "src.test_reflect.apply_reflect_padding#1",
      "cstart": 13,
      "cend": 13,
      "tstart": 15,
      "tend": 15
    },
    {
      "id": 21,
      "name": "step 21",
      "method": "src.test_reflect.apply_reflect_padding#1",
      "cstart": 13,
      "cend": 13,
      "tstart": 16,
      "tend": 16
    },
    {
      "id": 22,
      "name": "step 22",
      "method": "src.test_reflect.apply_reflect_padding#1",
      "cstart": 13,
      "cend": 13,
      "tstart": 17,
      "tend": 17
    },
    {
      "id": 23,
      "name": "step 23",
      "method": "src.test_reflect.apply_reflect_padding#1",
      "cstart": 13,
      "cend": 13,
      "tstart": 18,
      "tend": 18
    },
    {
      "id": 24,
      "name": "step 24",
      "method": "src.test_reflect.apply_reflect_padding#1",
      "cstart": 13,
      "cend": 13,
      "tstart": 19,
      "tend": 19
    },
    {
      "id": 25,
      "name": "step 25",
      "method": "src.test_reflect.apply_reflect_padding#1",
      "cstart": 13,
      "cend": 13,
      "tstart": 20,
      "tend": 20
    },
    {
      "id": 26,
      "name": "step 26",
      "method": "src.test_reflect.apply_reflect_padding#1",
      "cstart": 13,
      "cend": 13,
      "tstart": 21,
      "tend": 21
    },
    {
      "id": 27,
      "name": "step 27",
      "method": "src.test_reflect.apply_reflect_padding#1",
      "cstart": 13,
      "cend": 13,
      "tstart": 22,
      "tend": 22
    },
    {
      "id": 28,
      "name": "step 28",
      "method": "src.test_reflect.apply_reflect_padding#1",
      "cstart": 13,
      "cend": 13,
      "tstart": 23,
      "tend": 23
    },
    {
      "id": 29,
      "name": "step 29",
      "method": "src.test_reflect.apply_reflect_padding#1",
      "cstart": 13,
      "cend": 13,
      "tstart": 24,
      "tend": 24
    },
    {
      "id": 30,
      "name": "step 30",
      "method": "src.test_reflect.apply_reflect_padding#1",
      "cstart": 13,
      "cend": 13,
      "tstart": 25,
      "tend": 25
    },
    {
      "id": 31,
      "name": "step 31",
      "method": "src.test_reflect.apply_reflect_padding#1",
      "cstart": 13,
      "cend": 13,
      "tstart": 26,
      "tend": 26
    },
    {
      "id": 32,
      "name": "step 32",
      "method": "src.test_reflect.apply_reflect_padding#1",
      "cstart": 13,
      "cend": 13,
      "tstart": 27,
      "tend": 27
    },
    {
      "id": 33,
      "name": "step 33",
      "method": "src.test_reflect.apply_reflect_padding#1",
      "cstart": 13,
      "cend": 13,
      "tstart": 28,
      "tend": 28
    },
    {
      "id": 34,
      "name": "step 34",
      "method": "src.test_reflect.apply_reflect_padding#1",
      "cstart": 13,
      "cend": 13,
      "tstart": 29,
      "tend": 29
    },
    {
      "id": 35,
      "name": "step 35",
      "method": "src.test_reflect.apply_reflect_padding#1",
      "cstart": 13,
      "cend": 13,
      "tstart": 30,
      "tend": 30
    },
    {
      "id": 36,
      "name": "step 36",
      "method": "src.test_reflect.apply_reflect_padding#1",
      "cstart": 13,
      "cend": 13,
      "tstart": 31,
      "tend": 31
    },
    {
      "id": 37,
      "name": "step 37",
      "method": "src.test_reflect.apply_reflect_padding#1",
      "cstart": 13,
      "cend": 13,
      "tstart": 32,
      "tend": 32
    },
    {
      "id": 38,
      "name": "step 38",
      "method": "src.test_reflect.apply_reflect_padding#1",
      "cstart": 13,
      "cend": 13,
      "tstart": 33,
      "tend": 33
    },
    {
      "id": 39,
      "name": "step 39",
      "method": "src.test_reflect.apply_reflect_padding#1",
      "cstart": 13,
      "cend": 13,
      "tstart": 34,
      "tend": 34
    },
    {
      "id": 40,
      "name": "step 40",
      "method": "src.test_reflect.apply_reflect_padding#1",
      "cstart": 13,
      "cend": 13,
      "tstart": 35,
      "tend": 35
    },
    {
      "id": 41,
      "name": "step 41",
      "method": "src.test_reflect.apply_reflect_padding#1",
      "cstart": 13,
      "cend": 13,
      "tstart": 36,
      "tend": 36
    },
    {
      "id": 42,
      "name": "step 42",
      "method": "src.test_reflect.apply_reflect_padding#1",
      "cstart": 13,
      "cend": 13,
      "tstart": 37,
      "tend": 37
    },
    {
      "id": 43,
      "name": "step 43",
      "method": "src.test_reflect.apply_reflect_padding#1",
      "cstart": 13,
      "cend": 13,
      "tstart": 38,
      "tend": 38
    },
    {
      "id": 44,
      "name": "step 44",
      "method": "src.test_reflect.apply_reflect_padding#1",
      "cstart": 13,
      "cend": 13,
      "tstart": 39,
      "tend": 39
    },
    {
      "id": 45,
      "name": "step 45",
      "method": "src.test_reflect.apply_reflect_padding#1",
      "cstart": 13,
      "cend": 13,
      "tstart": 40,
      "tend": 40
    },
    {
      "id": 46,
      "name": "step 46",
      "method": "src.test_reflect.apply_reflect_padding#1",
      "cstart": 13,
      "cend": 13,
      "tstart": 41,
      "tend": 41
    },
    {
      "id": 47,
      "name": "step 47",
      "method": "src.test_reflect.apply_reflect_padding#1",
      "cstart": 13,
      "cend": 13,
      "tstart": 42,
      "tend": 42
    },
    {
      "id": 48,
      "name": "step 48",
      "method": "src.test_reflect.apply_reflect_padding#1",
      "cstart": 13,
      "cend": 13,
      "tstart": 43,
      "tend": 43
    },
    {
      "id": 49,
      "name": "step 49",
      "method": "src.test_reflect.apply_reflect_padding#1",
      "cstart": 13,
      "cend": 13,
      "tstart": 44,
      "tend": 44
    },
    {
      "id": 50,
      "name": "step 50",
      "method": "src.test_reflect.apply_reflect_padding#1",
      "cstart": 13,
      "cend": 13,
      "tstart": 45,
      "tend": 45
    },
    {
      "id": 51,
      "name": "step 51",
      "method": "src.test_reflect.apply_reflect_padding#1",
      "cstart": 13,
      "cend": 13,
      "tstart": 46,
      "tend": 46
    },
    {
      "id": 52,
      "name": "step 52",
      "method": "src.test_reflect.apply_reflect_padding#1",
      "cstart": 13,
      "cend": 13,
      "tstart": 47,
      "tend": 47
    },
    {
      "id": 53,
      "name": "step 53",
      "method": "src.test_reflect.apply_reflect_padding#1",
      "cstart": 13,
      "cend": 13,
      "tstart": 48,
      "tend": 48
    },
    {
      "id": 54,
      "name": "step 54",
      "method": "src.test_reflect.apply_reflect_padding#1",
      "cstart": 13,
      "cend": 13,
      "tstart": 49,
      "tend": 49
    },
    {
      "id": 55,
      "name": "step 55",
      "method": "src.test_reflect.apply_reflect_padding#1",
      "cstart": 13,
      "cend": 13,
      "tstart": 50,
      "tend": 50
    },
    {
      "id": 56,
      "name": "step 56",
      "method": "src.test_reflect.apply_reflect_padding#1",
      "cstart": 13,
      "cend": 13,
      "tstart": 51,
      "tend": 51
    },
    {
      "id": 57,
      "name": "step 57",
      "method": "src.test_reflect.apply_reflect_padding#1",
      "cstart": 13,
      "cend": 13,
      "tstart": 52,
      "tend": 52
    },
    {
      "id": 58,
      "name": "step 58",
      "method": "src.test_reflect.apply_reflect_padding#1",
      "cstart": 13,
      "cend": 13,
      "tstart": 53,
      "tend": 53
    },
    {
      "id": 59,
      "name": "step 59",
      "method": "src.test_reflect.apply_reflect_padding#1",
      "cstart": 13,
      "cend": 13,
      "tstart": 54,
      "tend": 54
    },
    {
      "id": 60,
      "name": "step 60",
      "method": "src.test_reflect.apply_reflect_padding#1",
      "cstart": 13,
      "cend": 13,
      "tstart": 55,
      "tend": 55
    },
    {
      "id": 61,
      "name": "step 61",
      "method": "src.test_reflect.apply_reflect_padding#1",
      "cstart": 13,
      "cend": 13,
      "tstart": 56,
      "tend": 56
    },
    {
      "id": 62,
      "name": "step 62",
      "method": "src.test_reflect.apply_reflect_padding#1",
      "cstart": 13,
      "cend": 13,
      "tstart": 57,
      "tend": 57
    },
    {
      "id": 63,
      "name": "step 63",
      "method": "src.test_reflect.apply_reflect_padding#1",
      "cstart": 13,
      "cend": 13,
      "tstart": 58,
      "tend": 58
    },
    {
      "id": 64,
      "name": "step 64",
      "method": "src.test_reflect.apply_reflect_padding#1",
      "cstart": 13,
      "cend": 13,
      "tstart": 59,
      "tend": 59
    },
    {
      "id": 65,
      "name": "step 65",
      "method": "src.test_reflect.apply_reflect_padding#1",
      "cstart": 13,
      "cend": 13,
      "tstart": 60,
      "tend": 60
    },
    {
      "id": 66,
      "name": "step 66",
      "method": "src.test_reflect.apply_reflect_padding#1",
      "cstart": 13,
      "cend": 13,
      "tstart": 61,
      "tend": 61
    },
    {
      "id": 67,
      "name": "step 67",
      "method": "src.test_reflect.apply_reflect_padding#1",
      "cstart": 13,
      "cend": 13,
      "tstart": 62,
      "tend": 62
    },
    {
      "id": 68,
      "name": "step 68",
      "method": "src.test_reflect.apply_reflect_padding#1",
      "cstart": 13,
      "cend": 13,
      "tstart": 63,
      "tend": 63
    },
    {
      "id": 69,
      "name": "step 69",
      "method": "src.test_reflect.apply_reflect_padding#1",
      "cstart": 13,
      "cend": 13,
      "tstart": 64,
      "tend": 64
    },
    {
      "id": 70,
      "name": "step 70",
      "method": "src.test_reflect.apply_reflect_padding#1",
      "cstart": 13,
      "cend": 13,
      "tstart": 65,
      "tend": 65
    },
    {
      "id": 71,
      "name": "step 71",
      "method": "src.test_reflect.apply_reflect_padding#1",
      "cstart": 13,
      "cend": 13,
      "tstart": 66,
      "tend": 66
    },
    {
      "id": 72,
      "name": "step 72",
      "method": "src.test_reflect.apply_reflect_padding#1",
      "cstart": 13,
      "cend": 13,
      "tstart": 67,
      "tend": 67
    },
    {
      "id": 73,
      "name": "step 73",
      "method": "src.test_reflect.apply_reflect_padding#1",
      "cstart": 13,
      "cend": 13,
      "tstart": 68,
      "tend": 68
    },
    {
      "id": 74,
      "name": "step 74",
      "method": "src.test_reflect.apply_reflect_padding#1",
      "cstart": 13,
      "cend": 13,
      "tstart": 69,
      "tend": 69
    },
    {
      "id": 75,
      "name": "step 75",
      "method": "src.test_reflect.apply_reflect_padding#1",
      "cstart": 13,
      "cend": 13,
      "tstart": 70,
      "tend": 70
    },
    {
      "id": 76,
      "name": "step 76",
      "method": "src.test_reflect.apply_reflect_padding#1",
      "cstart": 13,
      "cend": 13,
      "tstart": 71,
      "tend": 71
    },
    {
      "id": 77,
      "name": "step 77",
      "method": "src.test_reflect.apply_reflect_padding#1",
      "cstart": 13,
      "cend": 13,
      "tstart": 72,
      "tend": 72
    },
    {
      "id": 78,
      "name": "step 78",
      "method": "src.test_reflect.apply_reflect_padding#1",
      "cstart": 13,
      "cend": 13,
      "tstart": 73,
      "tend": 73
    },
    {
      "id": 79,
      "name": "step 79",
      "method": "src.test_reflect.apply_reflect_padding#1",
      "cstart": 13,
      "cend": 13,
      "tstart": 74,
      "tend": 74
    },
    {
      "id": 80,
      "name": "step 80",
      "method": "src.test_reflect.apply_reflect_padding#1",
      "cstart": 13,
      "cend": 13,
      "tstart": 75,
      "tend": 75
    },
    {
      "id": 81,
      "name": "step 81",
      "method": "src.test_reflect.apply_reflect_padding#1",
      "cstart": 13,
      "cend": 13,
      "tstart": 76,
      "tend": 76
    },
    {
      "id": 82,
      "name": "step 82",
      "method": "src.test_reflect.apply_reflect_padding#1",
      "cstart": 13,
      "cend": 13,
      "tstart": 77,
      "tend": 77
    },
    {
      "id": 83,
      "name": "step 83",
      "method": "src.test_reflect.apply_reflect_padding#1",
      "cstart": 13,
      "cend": 13,
      "tstart": 78,
      "tend": 78
    },
    {
      "id": 84,
      "name": "step 84",
      "method": "src.test_reflect.apply_reflect_padding#1",
      "cstart": 13,
      "cend": 13,
      "tstart": 79,
      "tend": 79
    },
    {
      "id": 85,
      "name": "step 85",
      "method": "src.test_reflect.apply_reflect_padding#1",
      "cstart": 13,
      "cend": 13,
      "tstart": 80,
      "tend": 80
    },
    {
      "id": 86,
      "name": "step 86",
      "method": "src.test_reflect.apply_reflect_padding#1",
      "cstart": 13,
      "cend": 13,
      "tstart": 81,
      "tend": 81
    },
    {
      "id": 87,
      "name": "step 87",
      "method": "src.test_reflect.apply_reflect_padding#1",
      "cstart": 13,
      "cend": 13,
      "tstart": 82,
      "tend": 82
    },
    {
      "id": 88,
      "name": "step 88",
      "method": "src.test_reflect.apply_reflect_padding#1",
      "cstart": 13,
      "cend": 13,
      "tstart": 83,
      "tend": 83
    },
    {
      "id": 89,
      "name": "step 89",
      "method": "src.test_reflect.apply_reflect_padding#1",
      "cstart": 13,
      "cend": 13,
      "tstart": 84,
      "tend": 84
    },
    {
      "id": 90,
      "name": "step 90",
      "method": "src.test_reflect.apply_reflect_padding#1",
      "cstart": 13,
      "cend": 13,
      "tstart": 85,
      "tend": 85
    },
    {
      "id": 91,
      "name": "step 91",
      "method": "src.test_reflect.apply_reflect_padding#1",
      "cstart": 13,
      "cend": 13,
      "tstart": 86,
      "tend": 86
    },
    {
      "id": 92,
      "name": "step 92",
      "method": "src.test_reflect.apply_reflect_padding#1",
      "cstart": 13,
      "cend": 13,
      "tstart": 87,
      "tend": 87
    },
    {
      "id": 93,
      "name": "step 93",
      "method": "src.test_reflect.apply_reflect_padding#1",
      "cstart": 13,
      "cend": 13,
      "tstart": 88,
      "tend": 88
    },
    {
      "id": 94,
      "name": "step 94",
      "method": "src.test_reflect.apply_reflect_padding#1",
      "cstart": 13,
      "cend": 13,
      "tstart": 89,
      "tend": 89
    },
    {
      "id": 95,
      "name": "step 95",
      "method": "src.test_reflect.apply_reflect_padding#1",
      "cstart": 13,
      "cend": 13,
      "tstart": 90,
      "tend": 90
    },
    {
      "id": 96,
      "name": "step 96",
      "method": "src.test_reflect.apply_reflect_padding#1",
      "cstart": 13,
      "cend": 13,
      "tstart": 91,
      "tend": 91
    },
    {
      "id": 97,
      "name": "step 97",
      "method": "src.test_reflect.apply_reflect_padding#1",
      "cstart": 15,
      "cend": 15,
      "tstart": 92,
      "tend": 92
    },
    {
      "id": 98,
      "name": "step 98",
      "method": "src.test_reflect.apply_reflect_padding#1",
      "cstart": 16,
      "cend": 16,
      "tstart": 93,
      "tend": 93
    },
    {
      "id": 99,
      "name": "step 99",
      "method": "src.test_reflect.apply_reflect_padding#1",
      "cstart": 17,
      "cend": 17,
      "tstart": 94,
      "tend": 94
    },
    {
      "id": 100,
      "name": "step 100",
      "method": "src.test_reflect.apply_reflect_padding#1",
      "cstart": 18,
      "cend": 18,
      "tstart": 95,
      "tend": 95
    },
    {
      "id": 101,
      "name": "step 101",
      "method": "src.test_reflect.apply_reflect_padding#1",
      "cstart": 19,
      "cend": 19,
      "tstart": 96,
      "tend": 96
    },
    {
      "id": 102,
      "name": "step 102",
      "method": "src.test_reflect.apply_reflect_padding#1",
      "cstart": 23,
      "cend": 23,
      "tstart": 97,
      "tend": 97
    },
    {
      "id": 103,
      "name": "step 103",
      "method": "src.test_reflect.apply_reflect_padding#1",
      "cstart": 17,
      "cend": 17,
      "tstart": 98,
      "tend": 98
    },
    {
      "id": 104,
      "name": "step 104",
      "method": "src.test_reflect.apply_reflect_padding#1",
      "cstart": 18,
      "cend": 18,
      "tstart": 99,
      "tend": 99
    },
    {
      "id": 105,
      "name": "step 105",
      "method": "src.test_reflect.apply_reflect_padding#1",
      "cstart": 19,
      "cend": 19,
      "tstart": 100,
      "tend": 100
    },
    {
      "id": 106,
      "name": "step 106",
      "method": "src.test_reflect.apply_reflect_padding#1",
      "cstart": 23,
      "cend": 23,
      "tstart": 101,
      "tend": 101
    },
    {
      "id": 107,
      "name": "step 107",
      "method": "src.test_reflect.apply_reflect_padding#1",
      "cstart": 17,
      "cend": 17,
      "tstart": 102,
      "tend": 102
    },
    {
      "id": 108,
      "name": "step 108",
      "method": "src.test_reflect.apply_reflect_padding#1",
      "cstart": 18,
      "cend": 18,
      "tstart": 103,
      "tend": 103
    },
    {
      "id": 109,
      "name": "step 109",
      "method": "src.test_reflect.apply_reflect_padding#1",
      "cstart": 19,
      "cend": 19,
      "tstart": 104,
      "tend": 104
    },
    {
      "id": 110,
      "name": "step 110",
      "method": "src.test_reflect.apply_reflect_padding#1",
      "cstart": 23,
      "cend": 23,
      "tstart": 105,
      "tend": 105
    },
    {
      "id": 111,
      "name": "step 111",
      "method": "src.test_reflect.apply_reflect_padding#1",
      "cstart": 17,
      "cend": 17,
      "tstart": 106,
      "tend": 106
    },
    {
      "id": 112,
      "name": "step 112",
      "method": "src.test_reflect.apply_reflect_padding#1",
      "cstart": 15,
      "cend": 15,
      "tstart": 107,
      "tend": 107
    },
    {
      "id": 113,
      "name": "step 113",
      "method": "src.test_reflect.apply_reflect_padding#1",
      "cstart": 16,
      "cend": 16,
      "tstart": 108,
      "tend": 108
    },
    {
      "id": 114,
      "name": "step 114",
      "method": "src.test_reflect.apply_reflect_padding#1",
      "cstart": 17,
      "cend": 17,
      "tstart": 109,
      "tend": 109
    },
    {
      "id": 115,
      "name": "step 115",
      "method": "src.test_reflect.apply_reflect_padding#1",
      "cstart": 18,
      "cend": 18,
      "tstart": 110,
      "tend": 110
    },
    {
      "id": 116,
      "name": "step 116",
      "method": "src.test_reflect.apply_reflect_padding#1",
      "cstart": 19,
      "cend": 19,
      "tstart": 111,
      "tend": 111
    },
    {
      "id": 117,
      "name": "step 117",
      "method": "src.test_reflect.apply_reflect_padding#1",
      "cstart": 23,
      "cend": 23,
      "tstart": 112,
      "tend": 112
    },
    {
      "id": 118,
      "name": "step 118",
      "method": "src.test_reflect.apply_reflect_padding#1",
      "cstart": 17,
      "cend": 17,
      "tstart": 113,
      "tend": 113
    },
    {
      "id": 119,
      "name": "step 119",
      "method": "src.test_reflect.apply_reflect_padding#1",
      "cstart": 18,
      "cend": 18,
      "tstart": 114,
      "tend": 114
    },
    {
      "id": 120,
      "name": "step 120",
      "method": "src.test_reflect.apply_reflect_padding#1",
      "cstart": 19,
      "cend": 19,
      "tstart": 115,
      "tend": 115
    },
    {
      "id": 121,
      "name": "step 121",
      "method": "src.test_reflect.apply_reflect_padding#1",
      "cstart": 23,
      "cend": 23,
      "tstart": 116,
      "tend": 116
    },
    {
      "id": 122,
      "name": "step 122",
      "method": "src.test_reflect.apply_reflect_padding#1",
      "cstart": 17,
      "cend": 17,
      "tstart": 117,
      "tend": 117
    },
    {
      "id": 123,
      "name": "step 123",
      "method": "src.test_reflect.apply_reflect_padding#1",
      "cstart": 18,
      "cend": 18,
      "tstart": 118,
      "tend": 118
    },
    {
      "id": 124,
      "name": "step 124",
      "method": "src.test_reflect.apply_reflect_padding#1",
      "cstart": 19,
      "cend": 19,
      "tstart": 119,
      "tend": 119
    },
    {
      "id": 125,
      "name": "step 125",
      "method": "src.test_reflect.apply_reflect_padding#1",
      "cstart": 23,
      "cend": 23,
      "tstart": 120,
      "tend": 120
    },
    {
      "id": 126,
      "name": "step 126",
      "method": "src.test_reflect.apply_reflect_padding#1",
      "cstart": 17,
      "cend": 17,
      "tstart": 121,
      "tend": 121
    },
    {
      "id": 127,
      "name": "step 127",
      "method": "src.test_reflect.apply_reflect_padding#1",
      "cstart": 15,
      "cend": 15,
      "tstart": 122,
      "tend": 122
    },
    {
      "id": 128,
      "name": "step 128",
      "method": "src.test_reflect.apply_reflect_padding#1",
      "cstart": 16,
      "cend": 16,
      "tstart": 123,
      "tend": 123
    },
    {
      "id": 129,
      "name": "step 129",
      "method": "src.test_reflect.apply_reflect_padding#1",
      "cstart": 17,
      "cend": 17,
      "tstart": 124,
      "tend": 124
    },
    {
      "id": 130,
      "name": "step 130",
      "method": "src.test_reflect.apply_reflect_padding#1",
      "cstart": 18,
      "cend": 18,
      "tstart": 125,
      "tend": 125
    },
    {
      "id": 131,
      "name": "step 131",
      "method": "src.test_reflect.apply_reflect_padding#1",
      "cstart": 19,
      "cend": 19,
      "tstart": 126,
      "tend": 126
    },
    {
      "id": 132,
      "name": "step 132",
      "method": "src.test_reflect.apply_reflect_padding#1",
      "cstart": 23,
      "cend": 23,
      "tstart": 127,
      "tend": 127
    },
    {
      "id": 133,
      "name": "step 133",
      "method": "src.test_reflect.apply_reflect_padding#1",
      "cstart": 17,
      "cend": 17,
      "tstart": 128,
      "tend": 128
    },
    {
      "id": 134,
      "name": "step 134",
      "method": "src.test_reflect.apply_reflect_padding#1",
      "cstart": 18,
      "cend": 18,
      "tstart": 129,
      "tend": 129
    },
    {
      "id": 135,
      "name": "step 135",
      "method": "src.test_reflect.apply_reflect_padding#1",
      "cstart": 19,
      "cend": 19,
      "tstart": 130,
      "tend": 130
    },
    {
      "id": 136,
      "name": "step 136",
      "method": "src.test_reflect.apply_reflect_padding#1",
      "cstart": 23,
      "cend": 23,
      "tstart": 131,
      "tend": 131
    },
    {
      "id": 137,
      "name": "step 137",
      "method": "src.test_reflect.apply_reflect_padding#1",
      "cstart": 17,
      "cend": 17,
      "tstart": 132,
      "tend": 132
    },
    {
      "id": 138,
      "name": "step 138",
      "method": "src.test_reflect.apply_reflect_padding#1",
      "cstart": 18,
      "cend": 18,
      "tstart": 133,
      "tend": 133
    },
    {
      "id": 139,
      "name": "step 139",
      "method": "src.test_reflect.apply_reflect_padding#1",
      "cstart": 19,
      "cend": 19,
      "tstart": 134,
      "tend": 134
    },
    {
      "id": 140,
      "name": "step 140",
      "method": "src.test_reflect.apply_reflect_padding#1",
      "cstart": 23,
      "cend": 23,
      "tstart": 135,
      "tend": 135
    },
    {
      "id": 141,
      "name": "step 141",
      "method": "src.test_reflect.apply_reflect_padding#1",
      "cstart": 17,
      "cend": 17,
      "tstart": 136,
      "tend": 136
    },
    {
      "id": 142,
      "name": "step 142",
      "method": "src.test_reflect.apply_reflect_padding#1",
      "cstart": 15,
      "cend": 15,
      "tstart": 137,
      "tend": 137
    },
    {
      "id": 143,
      "name": "step 143",
      "method": "src.test_reflect.apply_reflect_padding#1",
      "cstart": 25,
      "cend": 25,
      "tstart": 138,
      "tend": 138
    },
    {
      "id": 144,
      "name": "step 144",
      "method": "src.test_reflect.apply_reflect_padding#1",
      "cstart": 26,
      "cend": 26,
      "tstart": 139,
      "tend": 139
    },
    {
      "id": 145,
      "name": "step 145",
      "method": "src.test_reflect.apply_reflect_padding#1",
      "cstart": 27,
      "cend": 27,
      "tstart": 140,
      "tend": 140
    },
    {
      "id": 146,
      "name": "step 146",
      "method": "src.test_reflect.apply_reflect_padding#1",
      "cstart": 28,
      "cend": 28,
      "tstart": 141,
      "tend": 141
    },
    {
      "id": 147,
      "name": "step 147",
      "method": "src.test_reflect.apply_reflect_padding#1",
      "cstart": 30,
      "cend": 30,
      "tstart": 142,
      "tend": 142
    },
    {
      "id": 148,
      "name": "step 148",
      "method": "src.test_reflect.apply_reflect_padding#1",
      "cstart": 31,
      "cend": 31,
      "tstart": 143,
      "tend": 143
    },
    {
      "id": 149,
      "name": "step 149",
      "method": "src.test_reflect.apply_reflect_padding#1",
      "cstart": 33,
      "cend": 33,
      "tstart": 144,
      "tend": 144
    },
    {
      "id": 150,
      "name": "step 150",
      "method": "src.test_reflect.apply_reflect_padding#1",
      "cstart": 34,
      "cend": 34,
      "tstart": 145,
      "tend": 145
    },
    {
      "id": 151,
      "name": "step 151",
      "method": "src.test_reflect.apply_reflect_padding#1",
      "cstart": 39,
      "cend": 39,
      "tstart": 146,
      "tend": 146
    },
    {
      "id": 152,
      "name": "step 152",
      "method": "src.test_reflect.apply_reflect_padding#1",
      "cstart": 40,
      "cend": 40,
      "tstart": 147,
      "tend": 147
    },
    {
      "id": 153,
      "name": "step 153",
      "method": "src.test_reflect.apply_reflect_padding#1",
      "cstart": 33,
      "cend": 33,
      "tstart": 148,
      "tend": 148
    },
    {
      "id": 154,
      "name": "step 154",
      "method": "src.test_reflect.apply_reflect_padding#1",
      "cstart": 34,
      "cend": 34,
      "tstart": 149,
      "tend": 149
    },
    {
      "id": 155,
      "name": "step 155",
      "method": "src.test_reflect.apply_reflect_padding#1",
      "cstart": 39,
      "cend": 39,
      "tstart": 150,
      "tend": 150
    },
    {
      "id": 156,
      "name": "step 156",
      "method": "src.test_reflect.apply_reflect_padding#1",
      "cstart": 40,
      "cend": 40,
      "tstart": 151,
      "tend": 151
    },
    {
      "id": 157,
      "name": "step 157",
      "method": "src.test_reflect.apply_reflect_padding#1",
      "cstart": 33,
      "cend": 33,
      "tstart": 152,
      "tend": 152
    },
    {
      "id": 158,
      "name": "step 158",
      "method": "src.test_reflect.apply_reflect_padding#1",
      "cstart": 34,
      "cend": 34,
      "tstart": 153,
      "tend": 153
    },
    {
      "id": 159,
      "name": "step 159",
      "method": "src.test_reflect.apply_reflect_padding#1",
      "cstart": 39,
      "cend": 39,
      "tstart": 154,
      "tend": 154
    },
    {
      "id": 160,
      "name": "step 160",
      "method": "src.test_reflect.apply_reflect_padding#1",
      "cstart": 40,
      "cend": 40,
      "tstart": 155,
      "tend": 155
    },
    {
      "id": 161,
      "name": "step 161",
      "method": "src.test_reflect.apply_reflect_padding#1",
      "cstart": 33,
      "cend": 33,
      "tstart": 156,
      "tend": 156
    },
    {
      "id": 162,
      "name": "step 162",
      "method": "src.test_reflect.apply_reflect_padding#1",
      "cstart": 34,
      "cend": 34,
      "tstart": 157,
      "tend": 157
    },
    {
      "id": 163,
      "name": "step 163",
      "method": "src.test_reflect.apply_reflect_padding#1",
      "cstart": 39,
      "cend": 39,
      "tstart": 158,
      "tend": 158
    },
    {
      "id": 164,
      "name": "step 164",
      "method": "src.test_reflect.apply_reflect_padding#1",
      "cstart": 40,
      "cend": 40,
      "tstart": 159,
      "tend": 159
    },
    {
      "id": 165,
      "name": "step 165",
      "method": "src.test_reflect.apply_reflect_padding#1",
      "cstart": 33,
      "cend": 33,
      "tstart": 160,
      "tend": 160
    },
    {
      "id": 166,
      "name": "step 166",
      "method": "src.test_reflect.apply_reflect_padding#1",
      "cstart": 34,
      "cend": 34,
      "tstart": 161,
      "tend": 161
    },
    {
      "id": 167,
      "name": "step 167",
      "method": "src.test_reflect.apply_reflect_padding#1",
      "cstart": 39,
      "cend": 39,
      "tstart": 162,
      "tend": 162
    },
    {
      "id": 168,
      "name": "step 168",
      "method": "src.test_reflect.apply_reflect_padding#1",
      "cstart": 40,
      "cend": 40,
      "tstart": 163,
      "tend": 163
    },
    {
      "id": 169,
      "name": "step 169",
      "method": "src.test_reflect.apply_reflect_padding#1",
      "cstart": 33,
      "cend": 33,
      "tstart": 164,
      "tend": 164
    },
    {
      "id": 170,
      "name": "step 170",
      "method": "src.test_reflect.apply_reflect_padding#1",
      "cstart": 34,
      "cend": 34,
      "tstart": 165,
      "tend": 165
    },
    {
      "id": 171,
      "name": "step 171",
      "method": "src.test_reflect.apply_reflect_padding#1",
      "cstart": 39,
      "cend": 39,
      "tstart": 166,
      "tend": 166
    },
    {
      "id": 172,
      "name": "step 172",
      "method": "src.test_reflect.apply_reflect_padding#1",
      "cstart": 40,
      "cend": 40,
      "tstart": 167,
      "tend": 167
    },
    {
      "id": 173,
      "name": "step 173",
      "method": "src.test_reflect.apply_reflect_padding#1",
      "cstart": 33,
      "cend": 33,
      "tstart": 168,
      "tend": 168
    },
    {
      "id": 174,
      "name": "step 174",
      "method": "src.test_reflect.apply_reflect_padding#1",
      "cstart": 34,
      "cend": 34,
      "tstart": 169,
      "tend": 169
    },
    {
      "id": 175,
      "name": "step 175",
      "method": "src.test_reflect.apply_reflect_padding#1",
      "cstart": 39,
      "cend": 39,
      "tstart": 170,
      "tend": 170
    },
    {
      "id": 176,
      "name": "step 176",
      "method": "src.test_reflect.apply_reflect_padding#1",
      "cstart": 40,
      "cend": 40,
      "tstart": 171,
      "tend": 171
    },
    {
      "id": 177,
      "name": "step 177",
      "method": "src.test_reflect.apply_reflect_padding#1",
      "cstart": 33,
      "cend": 33,
      "tstart": 172,
      "tend": 172
    },
    {
      "id": 178,
      "name": "step 178",
      "method": "src.test_reflect.apply_reflect_padding#1",
      "cstart": 25,
      "cend": 25,
      "tstart": 173,
      "tend": 173
    },
    {
      "id": 179,
      "name": "step 179",
      "method": "src.test_reflect.apply_reflect_padding#1",
      "cstart": 26,
      "cend": 26,
      "tstart": 174,
      "tend": 174
    },
    {
      "id": 180,
      "name": "step 180",
      "method": "src.test_reflect.apply_reflect_padding#1",
      "cstart": 27,
      "cend": 27,
      "tstart": 175,
      "tend": 175
    },
    {
      "id": 181,
      "name": "step 181",
      "method": "src.test_reflect.apply_reflect_padding#1",
      "cstart": 28,
      "cend": 28,
      "tstart": 176,
      "tend": 176
    },
    {
      "id": 182,
      "name": "step 182",
      "method": "src.test_reflect.apply_reflect_padding#1",
      "cstart": 30,
      "cend": 30,
      "tstart": 177,
      "tend": 177
    },
    {
      "id": 183,
      "name": "step 183",
      "method": "src.test_reflect.apply_reflect_padding#1",
      "cstart": 31,
      "cend": 31,
      "tstart": 178,
      "tend": 178
    },
    {
      "id": 184,
      "name": "step 184",
      "method": "src.test_reflect.apply_reflect_padding#1",
      "cstart": 33,
      "cend": 33,
      "tstart": 179,
      "tend": 179
    },
    {
      "id": 185,
      "name": "step 185",
      "method": "src.test_reflect.apply_reflect_padding#1",
      "cstart": 34,
      "cend": 34,
      "tstart": 180,
      "tend": 180
    },
    {
      "id": 186,
      "name": "step 186",
      "method": "src.test_reflect.apply_reflect_padding#1",
      "cstart": 39,
      "cend": 39,
      "tstart": 181,
      "tend": 181
    },
    {
      "id": 187,
      "name": "step 187",
      "method": "src.test_reflect.apply_reflect_padding#1",
      "cstart": 40,
      "cend": 40,
      "tstart": 182,
      "tend": 182
    },
    {
      "id": 188,
      "name": "step 188",
      "method": "src.test_reflect.apply_reflect_padding#1",
      "cstart": 33,
      "cend": 33,
      "tstart": 183,
      "tend": 183
    },
    {
      "id": 189,
      "name": "step 189",
      "method": "src.test_reflect.apply_reflect_padding#1",
      "cstart": 34,
      "cend": 34,
      "tstart": 184,
      "tend": 184
    },
    {
      "id": 190,
      "name": "step 190",
      "method": "src.test_reflect.apply_reflect_padding#1",
      "cstart": 39,
      "cend": 39,
      "tstart": 185,
      "tend": 185
    },
    {
      "id": 191,
      "name": "step 191",
      "method": "src.test_reflect.apply_reflect_padding#1",
      "cstart": 40,
      "cend": 40,
      "tstart": 186,
      "tend": 186
    },
    {
      "id": 192,
      "name": "step 192",
      "method": "src.test_reflect.apply_reflect_padding#1",
      "cstart": 33,
      "cend": 33,
      "tstart": 187,
      "tend": 187
    },
    {
      "id": 193,
      "name": "step 193",
      "method": "src.test_reflect.apply_reflect_padding#1",
      "cstart": 34,
      "cend": 34,
      "tstart": 188,
      "tend": 188
    },
    {
      "id": 194,
      "name": "step 194",
      "method": "src.test_reflect.apply_reflect_padding#1",
      "cstart": 39,
      "cend": 39,
      "tstart": 189,
      "tend": 189
    },
    {
      "id": 195,
      "name": "step 195",
      "method": "src.test_reflect.apply_reflect_padding#1",
      "cstart": 40,
      "cend": 40,
      "tstart": 190,
      "tend": 190
    },
    {
      "id": 196,
      "name": "step 196",
      "method": "src.test_reflect.apply_reflect_padding#1",
      "cstart": 33,
      "cend": 33,
      "tstart": 191,
      "tend": 191
    },
    {
      "id": 197,
      "name": "step 197",
      "method": "src.test_reflect.apply_reflect_padding#1",
      "cstart": 34,
      "cend": 34,
      "tstart": 192,
      "tend": 192
    },
    {
      "id": 198,
      "name": "step 198",
      "method": "src.test_reflect.apply_reflect_padding#1",
      "cstart": 39,
      "cend": 39,
      "tstart": 193,
      "tend": 193
    },
    {
      "id": 199,
      "name": "step 199",
      "method": "src.test_reflect.apply_reflect_padding#1",
      "cstart": 40,
      "cend": 40,
      "tstart": 194,
      "tend": 194
    },
    {
      "id": 200,
      "name": "step 200",
      "method": "src.test_reflect.apply_reflect_padding#1",
      "cstart": 33,
      "cend": 33,
      "tstart": 195,
      "tend": 195
    },
    {
      "id": 201,
      "name": "step 201",
      "method": "src.test_reflect.apply_reflect_padding#1",
      "cstart": 34,
      "cend": 34,
      "tstart": 196,
      "tend": 196
    },
    {
      "id": 202,
      "name": "step 202",
      "method": "src.test_reflect.apply_reflect_padding#1",
      "cstart": 39,
      "cend": 39,
      "tstart": 197,
      "tend": 197
    },
    {
      "id": 203,
      "name": "step 203",
      "method": "src.test_reflect.apply_reflect_padding#1",
      "cstart": 40,
      "cend": 40,
      "tstart": 198,
      "tend": 198
    },
    {
      "id": 204,
      "name": "step 204",
      "method": "src.test_reflect.apply_reflect_padding#1",
      "cstart": 33,
      "cend": 33,
      "tstart": 199,
      "tend": 199
    },
    {
      "id": 205,
      "name": "step 205",
      "method": "src.test_reflect.apply_reflect_padding#1",
      "cstart": 34,
      "cend": 34,
      "tstart": 200,
      "tend": 200
    },
    {
      "id": 206,
      "name": "step 206",
      "method": "src.test_reflect.apply_reflect_padding#1",
      "cstart": 39,
      "cend": 39,
      "tstart": 201,
      "tend": 201
    },
    {
      "id": 207,
      "name": "step 207",
      "method": "src.test_reflect.apply_reflect_padding#1",
      "cstart": 40,
      "cend": 40,
      "tstart": 202,
      "tend": 202
    },
    {
      "id": 208,
      "name": "step 208",
      "method": "src.test_reflect.apply_reflect_padding#1",
      "cstart": 33,
      "cend": 33,
      "tstart": 203,
      "tend": 203
    },
    {
      "id": 209,
      "name": "step 209",
      "method": "src.test_reflect.apply_reflect_padding#1",
      "cstart": 34,
      "cend": 34,
      "tstart": 204,
      "tend": 204
    },
    {
      "id": 210,
      "name": "step 210",
      "method": "src.test_reflect.apply_reflect_padding#1",
      "cstart": 39,
      "cend": 39,
      "tstart": 205,
      "tend": 205
    },
    {
      "id": 211,
      "name": "step 211",
      "method": "src.test_reflect.apply_reflect_padding#1",
      "cstart": 40,
      "cend": 40,
      "tstart": 206,
      "tend": 206
    },
    {
      "id": 212,
      "name": "step 212",
      "method": "src.test_reflect.apply_reflect_padding#1",
      "cstart": 33,
      "cend": 33,
      "tstart": 207,
      "tend": 207
    },
    {
      "id": 213,
      "name": "step 213",
      "method": "src.test_reflect.apply_reflect_padding#1",
      "cstart": 25,
      "cend": 25,
      "tstart": 208,
      "tend": 208
    },
    {
      "id": 214,
      "name": "step 214",
      "method": "src.test_reflect.apply_reflect_padding#1",
      "cstart": 42,
      "cend": 42,
      "tstart": 209,
      "tend": 209
    },
    {
      "id": 215,
      "name": "step 215",
      "method": "src.test_reflect.apply_reflect_padding#1",
      "cstart": 43,
      "cend": 43,
      "tstart": 210,
      "tend": 210
    },
    {
      "id": 216,
      "name": "step 216",
      "method": "src.test_reflect.apply_reflect_padding#1",
      "cstart": 44,
      "cend": 44,
      "tstart": 211,
      "tend": 211
    },
    {
      "id": 217,
      "name": "step 217",
      "method": "src.test_reflect.apply_reflect_padding#1",
      "cstart": 45,
      "cend": 45,
      "tstart": 212,
      "tend": 212
    },
    {
      "id": 218,
      "name": "step 218",
      "method": "src.test_reflect.apply_reflect_padding#1",
      "cstart": 46,
      "cend": 46,
      "tstart": 213,
      "tend": 213
    },
    {
      "id": 219,
      "name": "step 219",
      "method": "src.test_reflect.apply_reflect_padding#1",
      "cstart": 49,
      "cend": 49,
      "tstart": 214,
      "tend": 214
    },
    {
      "id": 220,
      "name": "step 220",
      "method": "src.test_reflect.apply_reflect_padding#1",
      "cstart": 44,
      "cend": 44,
      "tstart": 215,
      "tend": 215
    },
    {
      "id": 221,
      "name": "step 221",
      "method": "src.test_reflect.apply_reflect_padding#1",
      "cstart": 45,
      "cend": 45,
      "tstart": 216,
      "tend": 216
    },
    {
      "id": 222,
      "name": "step 222",
      "method": "src.test_reflect.apply_reflect_padding#1",
      "cstart": 46,
      "cend": 46,
      "tstart": 217,
      "tend": 217
    },
    {
      "id": 223,
      "name": "step 223",
      "method": "src.test_reflect.apply_reflect_padding#1",
      "cstart": 49,
      "cend": 49,
      "tstart": 218,
      "tend": 218
    },
    {
      "id": 224,
      "name": "step 224",
      "method": "src.test_reflect.apply_reflect_padding#1",
      "cstart": 44,
      "cend": 44,
      "tstart": 219,
      "tend": 219
    },
    {
      "id": 225,
      "name": "step 225",
      "method": "src.test_reflect.apply_reflect_padding#1",
      "cstart": 45,
      "cend": 45,
      "tstart": 220,
      "tend": 220
    },
    {
      "id": 226,
      "name": "step 226",
      "method": "src.test_reflect.apply_reflect_padding#1",
      "cstart": 46,
      "cend": 46,
      "tstart": 221,
      "tend": 221
    },
    {
      "id": 227,
      "name": "step 227",
      "method": "src.test_reflect.apply_reflect_padding#1",
      "cstart": 49,
      "cend": 49,
      "tstart": 222,
      "tend": 222
    },
    {
      "id": 228,
      "name": "step 228",
      "method": "src.test_reflect.apply_reflect_padding#1",
      "cstart": 44,
      "cend": 44,
      "tstart": 223,
      "tend": 223
    },
    {
      "id": 229,
      "name": "step 229",
      "method": "src.test_reflect.apply_reflect_padding#1",
      "cstart": 45,
      "cend": 45,
      "tstart": 224,
      "tend": 224
    },
    {
      "id": 230,
      "name": "step 230",
      "method": "src.test_reflect.apply_reflect_padding#1",
      "cstart": 46,
      "cend": 46,
      "tstart": 225,
      "tend": 225
    },
    {
      "id": 231,
      "name": "step 231",
      "method": "src.test_reflect.apply_reflect_padding#1",
      "cstart": 49,
      "cend": 49,
      "tstart": 226,
      "tend": 226
    },
    {
      "id": 232,
      "name": "step 232",
      "method": "src.test_reflect.apply_reflect_padding#1",
      "cstart": 44,
      "cend": 44,
      "tstart": 227,
      "tend": 227
    },
    {
      "id": 233,
      "name": "step 233",
      "method": "src.test_reflect.apply_reflect_padding#1",
      "cstart": 45,
      "cend": 45,
      "tstart": 228,
      "tend": 228
    },
    {
      "id": 234,
      "name": "step 234",
      "method": "src.test_reflect.apply_reflect_padding#1",
      "cstart": 46,
      "cend": 46,
      "tstart": 229,
      "tend": 229
    },
    {
      "id": 235,
      "name": "step 235",
      "method": "src.test_reflect.apply_reflect_padding#1",
      "cstart": 49,
      "cend": 49,
      "tstart": 230,
      "tend": 230
    },
    {
      "id": 236,
      "name": "step 236",
      "method": "src.test_reflect.apply_reflect_padding#1",
      "cstart": 44,
      "cend": 44,
      "tstart": 231,
      "tend": 231
    },
    {
      "id": 237,
      "name": "step 237",
      "method": "src.test_reflect.apply_reflect_padding#1",
      "cstart": 45,
      "cend": 45,
      "tstart": 232,
      "tend": 232
    },
    {
      "id": 238,
      "name": "step 238",
      "method": "src.test_reflect.apply_reflect_padding#1",
      "cstart": 46,
      "cend": 46,
      "tstart": 233,
      "tend": 233
    },
    {
      "id": 239,
      "name": "step 239",
      "method": "src.test_reflect.apply_reflect_padding#1",
      "cstart": 49,
      "cend": 49,
      "tstart": 234,
      "tend": 234
    },
    {
      "id": 240,
      "name": "step 240",
      "method": "src.test_reflect.apply_reflect_padding#1",
      "cstart": 44,
      "cend": 44,
      "tstart": 235,
      "tend": 235
    },
    {
      "id": 241,
      "name": "step 241",
      "method": "src.test_reflect.apply_reflect_padding#1",
      "cstart": 45,
      "cend": 45,
      "tstart": 236,
      "tend": 236
    },
    {
      "id": 242,
      "name": "step 242",
      "method": "src.test_reflect.apply_reflect_padding#1",
      "cstart": 46,
      "cend": 46,
      "tstart": 237,
      "tend": 237
    },
    {
      "id": 243,
      "name": "step 243",
      "method": "src.test_reflect.apply_reflect_padding#1",
      "cstart": 49,
      "cend": 49,
      "tstart": 238,
      "tend": 238
    },
    {
      "id": 244,
      "name": "step 244",
      "method": "src.test_reflect.apply_reflect_padding#1",
      "cstart": 44,
      "cend": 44,
      "tstart": 239,
      "tend": 239
    },
    {
      "id": 245,
      "name": "step 245",
      "method": "src.test_reflect.apply_reflect_padding#1",
      "cstart": 43,
      "cend": 43,
      "tstart": 240,
      "tend": 240
    },
    {
      "id": 246,
      "name": "step 246",
      "method": "src.test_reflect.apply_reflect_padding#1",
      "cstart": 44,
      "cend": 44,
      "tstart": 241,
      "tend": 241
    },
    {
      "id": 247,
      "name": "step 247",
      "method": "src.test_reflect.apply_reflect_padding#1",
      "cstart": 45,
      "cend": 45,
      "tstart": 242,
      "tend": 242
    },
    {
      "id": 248,
      "name": "step 248",
      "method": "src.test_reflect.apply_reflect_padding#1",
      "cstart": 46,
      "cend": 46,
      "tstart": 243,
      "tend": 243
    },
    {
      "id": 249,
      "name": "step 249",
      "method": "src.test_reflect.apply_reflect_padding#1",
      "cstart": 49,
      "cend": 49,
      "tstart": 244,
      "tend": 244
    },
    {
      "id": 250,
      "name": "step 250",
      "method": "src.test_reflect.apply_reflect_padding#1",
      "cstart": 44,
      "cend": 44,
      "tstart": 245,
      "tend": 245
    },
    {
      "id": 251,
      "name": "step 251",
      "method": "src.test_reflect.apply_reflect_padding#1",
      "cstart": 45,
      "cend": 45,
      "tstart": 246,
      "tend": 246
    },
    {
      "id": 252,
      "name": "step 252",
      "method": "src.test_reflect.apply_reflect_padding#1",
      "cstart": 46,
      "cend": 46,
      "tstart": 247,
      "tend": 247
    },
    {
      "id": 253,
      "name": "step 253",
      "method": "src.test_reflect.apply_reflect_padding#1",
      "cstart": 49,
      "cend": 49,
      "tstart": 248,
      "tend": 248
    },
    {
      "id": 254,
      "name": "step 254",
      "method": "src.test_reflect.apply_reflect_padding#1",
      "cstart": 44,
      "cend": 44,
      "tstart": 249,
      "tend": 249
    },
    {
      "id": 255,
      "name": "step 255",
      "method": "src.test_reflect.apply_reflect_padding#1",
      "cstart": 45,
      "cend": 45,
      "tstart": 250,
      "tend": 250
    },
    {
      "id": 256,
      "name": "step 256",
      "method": "src.test_reflect.apply_reflect_padding#1",
      "cstart": 46,
      "cend": 46,
      "tstart": 251,
      "tend": 251
    },
    {
      "id": 257,
      "name": "step 257",
      "method": "src.test_reflect.apply_reflect_padding#1",
      "cstart": 49,
      "cend": 49,
      "tstart": 252,
      "tend": 252
    },
    {
      "id": 258,
      "name": "step 258",
      "method": "src.test_reflect.apply_reflect_padding#1",
      "cstart": 44,
      "cend": 44,
      "tstart": 253,
      "tend": 253
    },
    {
      "id": 259,
      "name": "step 259",
      "method": "src.test_reflect.apply_reflect_padding#1",
      "cstart": 45,
      "cend": 45,
      "tstart": 254,
      "tend": 254
    },
    {
      "id": 260,
      "name": "step 260",
      "method": "src.test_reflect.apply_reflect_padding#1",
      "cstart": 46,
      "cend": 46,
      "tstart": 255,
      "tend": 255
    },
    {
      "id": 261,
      "name": "step 261",
      "method": "src.test_reflect.apply_reflect_padding#1",
      "cstart": 49,
      "cend": 49,
      "tstart": 256,
      "tend": 256
    },
    {
      "id": 262,
      "name": "step 262",
      "method": "src.test_reflect.apply_reflect_padding#1",
      "cstart": 44,
      "cend": 44,
      "tstart": 257,
      "tend": 257
    },
    {
      "id": 263,
      "name": "step 263",
      "method": "src.test_reflect.apply_reflect_padding#1",
      "cstart": 45,
      "cend": 45,
      "tstart": 258,
      "tend": 258
    },
    {
      "id": 264,
      "name": "step 264",
      "method": "src.test_reflect.apply_reflect_padding#1",
      "cstart": 46,
      "cend": 46,
      "tstart": 259,
      "tend": 259
    },
    {
      "id": 265,
      "name": "step 265",
      "method": "src.test_reflect.apply_reflect_padding#1",
      "cstart": 49,
      "cend": 49,
      "tstart": 260,
      "tend": 260
    },
    {
      "id": 266,
      "name": "step 266",
      "method": "src.test_reflect.apply_reflect_padding#1",
      "cstart": 44,
      "cend": 44,
      "tstart": 261,
      "tend": 261
    },
    {
      "id": 267,
      "name": "step 267",
      "method": "src.test_reflect.apply_reflect_padding#1",
      "cstart": 45,
      "cend": 45,
      "tstart": 262,
      "tend": 262
    },
    {
      "id": 268,
      "name": "step 268",
      "method": "src.test_reflect.apply_reflect_padding#1",
      "cstart": 46,
      "cend": 46,
      "tstart": 263,
      "tend": 263
    },
    {
      "id": 269,
      "name": "step 269",
      "method": "src.test_reflect.apply_reflect_padding#1",
      "cstart": 49,
      "cend": 49,
      "tstart": 264,
      "tend": 264
    },
    {
      "id": 270,
      "name": "step 270",
      "method": "src.test_reflect.apply_reflect_padding#1",
      "cstart": 44,
      "cend": 44,
      "tstart": 265,
      "tend": 265
    },
    {
      "id": 271,
      "name": "step 271",
      "method": "src.test_reflect.apply_reflect_padding#1",
      "cstart": 45,
      "cend": 45,
      "tstart": 266,
      "tend": 266
    },
    {
      "id": 272,
      "name": "step 272",
      "method": "src.test_reflect.apply_reflect_padding#1",
      "cstart": 46,
      "cend": 46,
      "tstart": 267,
      "tend": 267
    },
    {
      "id": 273,
      "name": "step 273",
      "method": "src.test_reflect.apply_reflect_padding#1",
      "cstart": 49,
      "cend": 49,
      "tstart": 268,
      "tend": 268
    },
    {
      "id": 274,
      "name": "step 274",
      "method": "src.test_reflect.apply_reflect_padding#1",
      "cstart": 44,
      "cend": 44,
      "tstart": 269,
      "tend": 269
    },
    {
      "id": 275,
      "name": "step 275",
      "method": "src.test_reflect.apply_reflect_padding#1",
      "cstart": 43,
      "cend": 43,
      "tstart": 270,
      "tend": 270
    },
    {
      "id": 276,
      "name": "step 276",
      "method": "src.test_reflect.apply_reflect_padding#1",
      "cstart": 44,
      "cend": 44,
      "tstart": 271,
      "tend": 271
    },
    {
      "id": 277,
      "name": "step 277",
      "method": "src.test_reflect.apply_reflect_padding#1",
      "cstart": 45,
      "cend": 45,
      "tstart": 272,
      "tend": 272
    },
    {
      "id": 278,
      "name": "step 278",
      "method": "src.test_reflect.apply_reflect_padding#1",
      "cstart": 46,
      "cend": 46,
      "tstart": 273,
      "tend": 273
    },
    {
      "id": 279,
      "name": "step 279",
      "method": "src.test_reflect.apply_reflect_padding#1",
      "cstart": 49,
      "cend": 49,
      "tstart": 274,
      "tend": 274
    },
    {
      "id": 280,
      "name": "step 280",
      "method": "src.test_reflect.apply_reflect_padding#1",
      "cstart": 44,
      "cend": 44,
      "tstart": 275,
      "tend": 275
    },
    {
      "id": 281,
      "name": "step 281",
      "method": "src.test_reflect.apply_reflect_padding#1",
      "cstart": 45,
      "cend": 45,
      "tstart": 276,
      "tend": 276
    },
    {
      "id": 282,
      "name": "step 282",
      "method": "src.test_reflect.apply_reflect_padding#1",
      "cstart": 46,
      "cend": 46,
      "tstart": 277,
      "tend": 277
    },
    {
      "id": 283,
      "name": "step 283",
      "method": "src.test_reflect.apply_reflect_padding#1",
      "cstart": 49,
      "cend": 49,
      "tstart": 278,
      "tend": 278
    },
    {
      "id": 284,
      "name": "step 284",
      "method": "src.test_reflect.apply_reflect_padding#1",
      "cstart": 44,
      "cend": 44,
      "tstart": 279,
      "tend": 279
    },
    {
      "id": 285,
      "name": "step 285",
      "method": "src.test_reflect.apply_reflect_padding#1",
      "cstart": 45,
      "cend": 45,
      "tstart": 280,
      "tend": 280
    },
    {
      "id": 286,
      "name": "step 286",
      "method": "src.test_reflect.apply_reflect_padding#1",
      "cstart": 46,
      "cend": 46,
      "tstart": 281,
      "tend": 281
    },
    {
      "id": 287,
      "name": "step 287",
      "method": "src.test_reflect.apply_reflect_padding#1",
      "cstart": 49,
      "cend": 49,
      "tstart": 282,
      "tend": 282
    },
    {
      "id": 288,
      "name": "step 288",
      "method": "src.test_reflect.apply_reflect_padding#1",
      "cstart": 44,
      "cend": 44,
      "tstart": 283,
      "tend": 283
    },
    {
      "id": 289,
      "name": "step 289",
      "method": "src.test_reflect.apply_reflect_padding#1",
      "cstart": 45,
      "cend": 45,
      "tstart": 284,
      "tend": 284
    },
    {
      "id": 290,
      "name": "step 290",
      "method": "src.test_reflect.apply_reflect_padding#1",
      "cstart": 46,
      "cend": 46,
      "tstart": 285,
      "tend": 285
    },
    {
      "id": 291,
      "name": "step 291",
      "method": "src.test_reflect.apply_reflect_padding#1",
      "cstart": 49,
      "cend": 49,
      "tstart": 286,
      "tend": 286
    },
    {
      "id": 292,
      "name": "step 292",
      "method": "src.test_reflect.apply_reflect_padding#1",
      "cstart": 44,
      "cend": 44,
      "tstart": 287,
      "tend": 287
    },
    {
      "id": 293,
      "name": "step 293",
      "method": "src.test_reflect.apply_reflect_padding#1",
      "cstart": 45,
      "cend": 45,
      "tstart": 288,
      "tend": 288
    },
    {
      "id": 294,
      "name": "step 294",
      "method": "src.test_reflect.apply_reflect_padding#1",
      "cstart": 46,
      "cend": 46,
      "tstart": 289,
      "tend": 289
    },
    {
      "id": 295,
      "name": "step 295",
      "method": "src.test_reflect.apply_reflect_padding#1",
      "cstart": 49,
      "cend": 49,
      "tstart": 290,
      "tend": 290
    },
    {
      "id": 296,
      "name": "step 296",
      "method": "src.test_reflect.apply_reflect_padding#1",
      "cstart": 44,
      "cend": 44,
      "tstart": 291,
      "tend": 291
    },
    {
      "id": 297,
      "name": "step 297",
      "method": "src.test_reflect.apply_reflect_padding#1",
      "cstart": 45,
      "cend": 45,
      "tstart": 292,
      "tend": 292
    },
    {
      "id": 298,
      "name": "step 298",
      "method": "src.test_reflect.apply_reflect_padding#1",
      "cstart": 46,
      "cend": 46,
      "tstart": 293,
      "tend": 293
    },
    {
      "id": 299,
      "name": "step 299",
      "method": "src.test_reflect.apply_reflect_padding#1",
      "cstart": 49,
      "cend": 49,
      "tstart": 294,
      "tend": 294
    },
    {
      "id": 300,
      "name": "step 300",
      "method": "src.test_reflect.apply_reflect_padding#1",
      "cstart": 44,
      "cend": 44,
      "tstart": 295,
      "tend": 295
    },
    {
      "id": 301,
      "name": "step 301",
      "method": "src.test_reflect.apply_reflect_padding#1",
      "cstart": 45,
      "cend": 45,
      "tstart": 296,
      "tend": 296
    },
    {
      "id": 302,
      "name": "step 302",
      "method": "src.test_reflect.apply_reflect_padding#1",
      "cstart": 46,
      "cend": 46,
      "tstart": 297,
      "tend": 297
    },
    {
      "id": 303,
      "name": "step 303",
      "method": "src.test_reflect.apply_reflect_padding#1",
      "cstart": 49,
      "cend": 49,
      "tstart": 298,
      "tend": 298
    },
    {
      "id": 304,
      "name": "step 304",
      "method": "src.test_reflect.apply_reflect_padding#1",
      "cstart": 44,
      "cend": 44,
      "tstart": 299,
      "tend": 299
    },
    {
      "id": 305,
      "name": "step 305",
      "method": "src.test_reflect.apply_reflect_padding#1",
      "cstart": 43,
      "cend": 43,
      "tstart": 300,
      "tend": 300
    },
    {
      "id": 306,
      "name": "step 306",
      "method": "src.test_reflect.apply_reflect_padding#1",
      "cstart": 44,
      "cend": 44,
      "tstart": 301,
      "tend": 301
    },
    {
      "id": 307,
      "name": "step 307",
      "method": "src.test_reflect.apply_reflect_padding#1",
      "cstart": 45,
      "cend": 45,
      "tstart": 302,
      "tend": 302
    },
    {
      "id": 308,
      "name": "step 308",
      "method": "src.test_reflect.apply_reflect_padding#1",
      "cstart": 46,
      "cend": 46,
      "tstart": 303,
      "tend": 303
    },
    {
      "id": 309,
      "name": "step 309",
      "method": "src.test_reflect.apply_reflect_padding#1",
      "cstart": 49,
      "cend": 49,
      "tstart": 304,
      "tend": 304
    },
    {
      "id": 310,
      "name": "step 310",
      "method": "src.test_reflect.apply_reflect_padding#1",
      "cstart": 44,
      "cend": 44,
      "tstart": 305,
      "tend": 305
    },
    {
      "id": 311,
      "name": "step 311",
      "method": "src.test_reflect.apply_reflect_padding#1",
      "cstart": 45,
      "cend": 45,
      "tstart": 306,
      "tend": 306
    },
    {
      "id": 312,
      "name": "step 312",
      "method": "src.test_reflect.apply_reflect_padding#1",
      "cstart": 46,
      "cend": 46,
      "tstart": 307,
      "tend": 307
    },
    {
      "id": 313,
      "name": "step 313",
      "method": "src.test_reflect.apply_reflect_padding#1",
      "cstart": 49,
      "cend": 49,
      "tstart": 308,
      "tend": 308
    },
    {
      "id": 314,
      "name": "step 314",
      "method": "src.test_reflect.apply_reflect_padding#1",
      "cstart": 44,
      "cend": 44,
      "tstart": 309,
      "tend": 309
    },
    {
      "id": 315,
      "name": "step 315",
      "method": "src.test_reflect.apply_reflect_padding#1",
      "cstart": 45,
      "cend": 45,
      "tstart": 310,
      "tend": 310
    },
    {
      "id": 316,
      "name": "step 316",
      "method": "src.test_reflect.apply_reflect_padding#1",
      "cstart": 46,
      "cend": 46,
      "tstart": 311,
      "tend": 311
    },
    {
      "id": 317,
      "name": "step 317",
      "method": "src.test_reflect.apply_reflect_padding#1",
      "cstart": 49,
      "cend": 49,
      "tstart": 312,
      "tend": 312
    },
    {
      "id": 318,
      "name": "step 318",
      "method": "src.test_reflect.apply_reflect_padding#1",
      "cstart": 44,
      "cend": 44,
      "tstart": 313,
      "tend": 313
    },
    {
      "id": 319,
      "name": "step 319",
      "method": "src.test_reflect.apply_reflect_padding#1",
      "cstart": 45,
      "cend": 45,
      "tstart": 314,
      "tend": 314
    },
    {
      "id": 320,
      "name": "step 320",
      "method": "src.test_reflect.apply_reflect_padding#1",
      "cstart": 46,
      "cend": 46,
      "tstart": 315,
      "tend": 315
    },
    {
      "id": 321,
      "name": "step 321",
      "method": "src.test_reflect.apply_reflect_padding#1",
      "cstart": 49,
      "cend": 49,
      "tstart": 316,
      "tend": 316
    },
    {
      "id": 322,
      "name": "step 322",
      "method": "src.test_reflect.apply_reflect_padding#1",
      "cstart": 44,
      "cend": 44,
      "tstart": 317,
      "tend": 317
    },
    {
      "id": 323,
      "name": "step 323",
      "method": "src.test_reflect.apply_reflect_padding#1",
      "cstart": 45,
      "cend": 45,
      "tstart": 318,
      "tend": 318
    },
    {
      "id": 324,
      "name": "step 324",
      "method": "src.test_reflect.apply_reflect_padding#1",
      "cstart": 46,
      "cend": 46,
      "tstart": 319,
      "tend": 319
    },
    {
      "id": 325,
      "name": "step 325",
      "method": "src.test_reflect.apply_reflect_padding#1",
      "cstart": 49,
      "cend": 49,
      "tstart": 320,
      "tend": 320
    },
    {
      "id": 326,
      "name": "step 326",
      "method": "src.test_reflect.apply_reflect_padding#1",
      "cstart": 44,
      "cend": 44,
      "tstart": 321,
      "tend": 321
    },
    {
      "id": 327,
      "name": "step 327",
      "method": "src.test_reflect.apply_reflect_padding#1",
      "cstart": 45,
      "cend": 45,
      "tstart": 322,
      "tend": 322
    },
    {
      "id": 328,
      "name": "step 328",
      "method": "src.test_reflect.apply_reflect_padding#1",
      "cstart": 46,
      "cend": 46,
      "tstart": 323,
      "tend": 323
    },
    {
      "id": 329,
      "name": "step 329",
      "method": "src.test_reflect.apply_reflect_padding#1",
      "cstart": 49,
      "cend": 49,
      "tstart": 324,
      "tend": 324
    },
    {
      "id": 330,
      "name": "step 330",
      "method": "src.test_reflect.apply_reflect_padding#1",
      "cstart": 44,
      "cend": 44,
      "tstart": 325,
      "tend": 325
    },
    {
      "id": 331,
      "name": "step 331",
      "method": "src.test_reflect.apply_reflect_padding#1",
      "cstart": 45,
      "cend": 45,
      "tstart": 326,
      "tend": 326
    },
    {
      "id": 332,
      "name": "step 332",
      "method": "src.test_reflect.apply_reflect_padding#1",
      "cstart": 46,
      "cend": 46,
      "tstart": 327,
      "tend": 327
    },
    {
      "id": 333,
      "name": "step 333",
      "method": "src.test_reflect.apply_reflect_padding#1",
      "cstart": 49,
      "cend": 49,
      "tstart": 328,
      "tend": 328
    },
    {
      "id": 334,
      "name": "step 334",
      "method": "src.test_reflect.apply_reflect_padding#1",
      "cstart": 44,
      "cend": 44,
      "tstart": 329,
      "tend": 329
    },
    {
      "id": 335,
      "name": "step 335",
      "method": "src.test_reflect.apply_reflect_padding#1",
      "cstart": 43,
      "cend": 43,
      "tstart": 330,
      "tend": 330
    },
    {
      "id": 336,
      "name": "step 336",
      "method": "src.test_reflect.apply_reflect_padding#1",
      "cstart": 44,
      "cend": 44,
      "tstart": 331,
      "tend": 331
    },
    {
      "id": 337,
      "name": "step 337",
      "method": "src.test_reflect.apply_reflect_padding#1",
      "cstart": 45,
      "cend": 45,
      "tstart": 332,
      "tend": 332
    },
    {
      "id": 338,
      "name": "step 338",
      "method": "src.test_reflect.apply_reflect_padding#1",
      "cstart": 46,
      "cend": 46,
      "tstart": 333,
      "tend": 333
    },
    {
      "id": 339,
      "name": "step 339",
      "method": "src.test_reflect.apply_reflect_padding#1",
      "cstart": 49,
      "cend": 49,
      "tstart": 334,
      "tend": 334
    },
    {
      "id": 340,
      "name": "step 340",
      "method": "src.test_reflect.apply_reflect_padding#1",
      "cstart": 44,
      "cend": 44,
      "tstart": 335,
      "tend": 335
    },
    {
      "id": 341,
      "name": "step 341",
      "method": "src.test_reflect.apply_reflect_padding#1",
      "cstart": 45,
      "cend": 45,
      "tstart": 336,
      "tend": 336
    },
    {
      "id": 342,
      "name": "step 342",
      "method": "src.test_reflect.apply_reflect_padding#1",
      "cstart": 46,
      "cend": 46,
      "tstart": 337,
      "tend": 337
    },
    {
      "id": 343,
      "name": "step 343",
      "method": "src.test_reflect.apply_reflect_padding#1",
      "cstart": 49,
      "cend": 49,
      "tstart": 338,
      "tend": 338
    },
    {
      "id": 344,
      "name": "step 344",
      "method": "src.test_reflect.apply_reflect_padding#1",
      "cstart": 44,
      "cend": 44,
      "tstart": 339,
      "tend": 339
    },
    {
      "id": 345,
      "name": "step 345",
      "method": "src.test_reflect.apply_reflect_padding#1",
      "cstart": 45,
      "cend": 45,
      "tstart": 340,
      "tend": 340
    },
    {
      "id": 346,
      "name": "step 346",
      "method": "src.test_reflect.apply_reflect_padding#1",
      "cstart": 46,
      "cend": 46,
      "tstart": 341,
      "tend": 341
    },
    {
      "id": 347,
      "name": "step 347",
      "method": "src.test_reflect.apply_reflect_padding#1",
      "cstart": 49,
      "cend": 49,
      "tstart": 342,
      "tend": 342
    },
    {
      "id": 348,
      "name": "step 348",
      "method": "src.test_reflect.apply_reflect_padding#1",
      "cstart": 44,
      "cend": 44,
      "tstart": 343,
      "tend": 343
    },
    {
      "id": 349,
      "name": "step 349",
      "method": "src.test_reflect.apply_reflect_padding#1",
      "cstart": 45,
      "cend": 45,
      "tstart": 344,
      "tend": 344
    },
    {
      "id": 350,
      "name": "step 350",
      "method": "src.test_reflect.apply_reflect_padding#1",
      "cstart": 46,
      "cend": 46,
      "tstart": 345,
      "tend": 345
    },
    {
      "id": 351,
      "name": "step 351",
      "method": "src.test_reflect.apply_reflect_padding#1",
      "cstart": 49,
      "cend": 49,
      "tstart": 346,
      "tend": 346
    },
    {
      "id": 352,
      "name": "step 352",
      "method": "src.test_reflect.apply_reflect_padding#1",
      "cstart": 44,
      "cend": 44,
      "tstart": 347,
      "tend": 347
    },
    {
      "id": 353,
      "name": "step 353",
      "method": "src.test_reflect.apply_reflect_padding#1",
      "cstart": 45,
      "cend": 45,
      "tstart": 348,
      "tend": 348
    },
    {
      "id": 354,
      "name": "step 354",
      "method": "src.test_reflect.apply_reflect_padding#1",
      "cstart": 46,
      "cend": 46,
      "tstart": 349,
      "tend": 349
    },
    {
      "id": 355,
      "name": "step 355",
      "method": "src.test_reflect.apply_reflect_padding#1",
      "cstart": 49,
      "cend": 49,
      "tstart": 350,
      "tend": 350
    },
    {
      "id": 356,
      "name": "step 356",
      "method": "src.test_reflect.apply_reflect_padding#1",
      "cstart": 44,
      "cend": 44,
      "tstart": 351,
      "tend": 351
    },
    {
      "id": 357,
      "name": "step 357",
      "method": "src.test_reflect.apply_reflect_padding#1",
      "cstart": 45,
      "cend": 45,
      "tstart": 352,
      "tend": 352
    },
    {
      "id": 358,
      "name": "step 358",
      "method": "src.test_reflect.apply_reflect_padding#1",
      "cstart": 46,
      "cend": 46,
      "tstart": 353,
      "tend": 353
    },
    {
      "id": 359,
      "name": "step 359",
      "method": "src.test_reflect.apply_reflect_padding#1",
      "cstart": 49,
      "cend": 49,
      "tstart": 354,
      "tend": 354
    },
    {
      "id": 360,
      "name": "step 360",
      "method": "src.test_reflect.apply_reflect_padding#1",
      "cstart": 44,
      "cend": 44,
      "tstart": 355,
      "tend": 355
    },
    {
      "id": 361,
      "name": "step 361",
      "method": "src.test_reflect.apply_reflect_padding#1",
      "cstart": 45,
      "cend": 45,
      "tstart": 356,
      "tend": 356
    },
    {
      "id": 362,
      "name": "step 362",
      "method": "src.test_reflect.apply_reflect_padding#1",
      "cstart": 46,
      "cend": 46,
      "tstart": 357,
      "tend": 357
    },
    {
      "id": 363,
      "name": "step 363",
      "method": "src.test_reflect.apply_reflect_padding#1",
      "cstart": 49,
      "cend": 49,
      "tstart": 358,
      "tend": 358
    },
    {
      "id": 364,
      "name": "step 364",
      "method": "src.test_reflect.apply_reflect_padding#1",
      "cstart": 44,
      "cend": 44,
      "tstart": 359,
      "tend": 359
    },
    {
      "id": 365,
      "name": "step 365",
      "method": "src.test_reflect.apply_reflect_padding#1",
      "cstart": 43,
      "cend": 43,
      "tstart": 360,
      "tend": 360
    },
    {
      "id": 366,
      "name": "step 366",
      "method": "src.test_reflect.apply_reflect_padding#1",
      "cstart": 44,
      "cend": 44,
      "tstart": 361,
      "tend": 361
    },
    {
      "id": 367,
      "name": "step 367",
      "method": "src.test_reflect.apply_reflect_padding#1",
      "cstart": 45,
      "cend": 45,
      "tstart": 362,
      "tend": 362
    },
    {
      "id": 368,
      "name": "step 368",
      "method": "src.test_reflect.apply_reflect_padding#1",
      "cstart": 46,
      "cend": 46,
      "tstart": 363,
      "tend": 363
    },
    {
      "id": 369,
      "name": "step 369",
      "method": "src.test_reflect.apply_reflect_padding#1",
      "cstart": 49,
      "cend": 49,
      "tstart": 364,
      "tend": 364
    },
    {
      "id": 370,
      "name": "step 370",
      "method": "src.test_reflect.apply_reflect_padding#1",
      "cstart": 44,
      "cend": 44,
      "tstart": 365,
      "tend": 365
    },
    {
      "id": 371,
      "name": "step 371",
      "method": "src.test_reflect.apply_reflect_padding#1",
      "cstart": 45,
      "cend": 45,
      "tstart": 366,
      "tend": 366
    },
    {
      "id": 372,
      "name": "step 372",
      "method": "src.test_reflect.apply_reflect_padding#1",
      "cstart": 46,
      "cend": 46,
      "tstart": 367,
      "tend": 367
    },
    {
      "id": 373,
      "name": "step 373",
      "method": "src.test_reflect.apply_reflect_padding#1",
      "cstart": 49,
      "cend": 49,
      "tstart": 368,
      "tend": 368
    },
    {
      "id": 374,
      "name": "step 374",
      "method": "src.test_reflect.apply_reflect_padding#1",
      "cstart": 44,
      "cend": 44,
      "tstart": 369,
      "tend": 369
    },
    {
      "id": 375,
      "name": "step 375",
      "method": "src.test_reflect.apply_reflect_padding#1",
      "cstart": 45,
      "cend": 45,
      "tstart": 370,
      "tend": 370
    },
    {
      "id": 376,
      "name": "step 376",
      "method": "src.test_reflect.apply_reflect_padding#1",
      "cstart": 46,
      "cend": 46,
      "tstart": 371,
      "tend": 371
    },
    {
      "id": 377,
      "name": "step 377",
      "method": "src.test_reflect.apply_reflect_padding#1",
      "cstart": 49,
      "cend": 49,
      "tstart": 372,
      "tend": 372
    },
    {
      "id": 378,
      "name": "step 378",
      "method": "src.test_reflect.apply_reflect_padding#1",
      "cstart": 44,
      "cend": 44,
      "tstart": 373,
      "tend": 373
    },
    {
      "id": 379,
      "name": "step 379",
      "method": "src.test_reflect.apply_reflect_padding#1",
      "cstart": 45,
      "cend": 45,
      "tstart": 374,
      "tend": 374
    },
    {
      "id": 380,
      "name": "step 380",
      "method": "src.test_reflect.apply_reflect_padding#1",
      "cstart": 46,
      "cend": 46,
      "tstart": 375,
      "tend": 375
    },
    {
      "id": 381,
      "name": "step 381",
      "method": "src.test_reflect.apply_reflect_padding#1",
      "cstart": 49,
      "cend": 49,
      "tstart": 376,
      "tend": 376
    },
    {
      "id": 382,
      "name": "step 382",
      "method": "src.test_reflect.apply_reflect_padding#1",
      "cstart": 44,
      "cend": 44,
      "tstart": 377,
      "tend": 377
    },
    {
      "id": 383,
      "name": "step 383",
      "method": "src.test_reflect.apply_reflect_padding#1",
      "cstart": 45,
      "cend": 45,
      "tstart": 378,
      "tend": 378
    },
    {
      "id": 384,
      "name": "step 384",
      "method": "src.test_reflect.apply_reflect_padding#1",
      "cstart": 46,
      "cend": 46,
      "tstart": 379,
      "tend": 379
    },
    {
      "id": 385,
      "name": "step 385",
      "method": "src.test_reflect.apply_reflect_padding#1",
      "cstart": 49,
      "cend": 49,
      "tstart": 380,
      "tend": 380
    },
    {
      "id": 386,
      "name": "step 386",
      "method": "src.test_reflect.apply_reflect_padding#1",
      "cstart": 44,
      "cend": 44,
      "tstart": 381,
      "tend": 381
    },
    {
      "id": 387,
      "name": "step 387",
      "method": "src.test_reflect.apply_reflect_padding#1",
      "cstart": 45,
      "cend": 45,
      "tstart": 382,
      "tend": 382
    },
    {
      "id": 388,
      "name": "step 388",
      "method": "src.test_reflect.apply_reflect_padding#1",
      "cstart": 46,
      "cend": 46,
      "tstart": 383,
      "tend": 383
    },
    {
      "id": 389,
      "name": "step 389",
      "method": "src.test_reflect.apply_reflect_padding#1",
      "cstart": 49,
      "cend": 49,
      "tstart": 384,
      "tend": 384
    },
    {
      "id": 390,
      "name": "step 390",
      "method": "src.test_reflect.apply_reflect_padding#1",
      "cstart": 44,
      "cend": 44,
      "tstart": 385,
      "tend": 385
    },
    {
      "id": 391,
      "name": "step 391",
      "method": "src.test_reflect.apply_reflect_padding#1",
      "cstart": 45,
      "cend": 45,
      "tstart": 386,
      "tend": 386
    },
    {
      "id": 392,
      "name": "step 392",
      "method": "src.test_reflect.apply_reflect_padding#1",
      "cstart": 46,
      "cend": 46,
      "tstart": 387,
      "tend": 387
    },
    {
      "id": 393,
      "name": "step 393",
      "method": "src.test_reflect.apply_reflect_padding#1",
      "cstart": 49,
      "cend": 49,
      "tstart": 388,
      "tend": 388
    },
    {
      "id": 394,
      "name": "step 394",
      "method": "src.test_reflect.apply_reflect_padding#1",
      "cstart": 44,
      "cend": 44,
      "tstart": 389,
      "tend": 389
    },
    {
      "id": 395,
      "name": "step 395",
      "method": "src.test_reflect.apply_reflect_padding#1",
      "cstart": 43,
      "cend": 43,
      "tstart": 390,
      "tend": 390
    },
    {
      "id": 396,
      "name": "step 396",
      "method": "src.test_reflect.apply_reflect_padding#1",
      "cstart": 44,
      "cend": 44,
      "tstart": 391,
      "tend": 391
    },
    {
      "id": 397,
      "name": "step 397",
      "method": "src.test_reflect.apply_reflect_padding#1",
      "cstart": 45,
      "cend": 45,
      "tstart": 392,
      "tend": 392
    },
    {
      "id": 398,
      "name": "step 398",
      "method": "src.test_reflect.apply_reflect_padding#1",
      "cstart": 46,
      "cend": 46,
      "tstart": 393,
      "tend": 393
    },
    {
      "id": 399,
      "name": "step 399",
      "method": "src.test_reflect.apply_reflect_padding#1",
      "cstart": 49,
      "cend": 49,
      "tstart": 394,
      "tend": 394
    },
    {
      "id": 400,
      "name": "step 400",
      "method": "src.test_reflect.apply_reflect_padding#1",
      "cstart": 44,
      "cend": 44,
      "tstart": 395,
      "tend": 395
    },
    {
      "id": 401,
      "name": "step 401",
      "method": "src.test_reflect.apply_reflect_padding#1",
      "cstart": 45,
      "cend": 45,
      "tstart": 396,
      "tend": 396
    },
    {
      "id": 402,
      "name": "step 402",
      "method": "src.test_reflect.apply_reflect_padding#1",
      "cstart": 46,
      "cend": 46,
      "tstart": 397,
      "tend": 397
    },
    {
      "id": 403,
      "name": "step 403",
      "method": "src.test_reflect.apply_reflect_padding#1",
      "cstart": 49,
      "cend": 49,
      "tstart": 398,
      "tend": 398
    },
    {
      "id": 404,
      "name": "step 404",
      "method": "src.test_reflect.apply_reflect_padding#1",
      "cstart": 44,
      "cend": 44,
      "tstart": 399,
      "tend": 399
    },
    {
      "id": 405,
      "name": "step 405",
      "method": "src.test_reflect.apply_reflect_padding#1",
      "cstart": 45,
      "cend": 45,
      "tstart": 400,
      "tend": 400
    },
    {
      "id": 406,
      "name": "step 406",
      "method": "src.test_reflect.apply_reflect_padding#1",
      "cstart": 46,
      "cend": 46,
      "tstart": 401,
      "tend": 401
    },
    {
      "id": 407,
      "name": "step 407",
      "method": "src.test_reflect.apply_reflect_padding#1",
      "cstart": 49,
      "cend": 49,
      "tstart": 402,
      "tend": 402
    },
    {
      "id": 408,
      "name": "step 408",
      "method": "src.test_reflect.apply_reflect_padding#1",
      "cstart": 44,
      "cend": 44,
      "tstart": 403,
      "tend": 403
    },
    {
      "id": 409,
      "name": "step 409",
      "method": "src.test_reflect.apply_reflect_padding#1",
      "cstart": 45,
      "cend": 45,
      "tstart": 404,
      "tend": 404
    },
    {
      "id": 410,
      "name": "step 410",
      "method": "src.test_reflect.apply_reflect_padding#1",
      "cstart": 46,
      "cend": 46,
      "tstart": 405,
      "tend": 405
    },
    {
      "id": 411,
      "name": "step 411",
      "method": "src.test_reflect.apply_reflect_padding#1",
      "cstart": 49,
      "cend": 49,
      "tstart": 406,
      "tend": 406
    },
    {
      "id": 412,
      "name": "step 412",
      "method": "src.test_reflect.apply_reflect_padding#1",
      "cstart": 44,
      "cend": 44,
      "tstart": 407,
      "tend": 407
    },
    {
      "id": 413,
      "name": "step 413",
      "method": "src.test_reflect.apply_reflect_padding#1",
      "cstart": 45,
      "cend": 45,
      "tstart": 408,
      "tend": 408
    },
    {
      "id": 414,
      "name": "step 414",
      "method": "src.test_reflect.apply_reflect_padding#1",
      "cstart": 46,
      "cend": 46,
      "tstart": 409,
      "tend": 409
    },
    {
      "id": 415,
      "name": "step 415",
      "method": "src.test_reflect.apply_reflect_padding#1",
      "cstart": 49,
      "cend": 49,
      "tstart": 410,
      "tend": 410
    },
    {
      "id": 416,
      "name": "step 416",
      "method": "src.test_reflect.apply_reflect_padding#1",
      "cstart": 44,
      "cend": 44,
      "tstart": 411,
      "tend": 411
    },
    {
      "id": 417,
      "name": "step 417",
      "method": "src.test_reflect.apply_reflect_padding#1",
      "cstart": 45,
      "cend": 45,
      "tstart": 412,
      "tend": 412
    },
    {
      "id": 418,
      "name": "step 418",
      "method": "src.test_reflect.apply_reflect_padding#1",
      "cstart": 46,
      "cend": 46,
      "tstart": 413,
      "tend": 413
    },
    {
      "id": 419,
      "name": "step 419",
      "method": "src.test_reflect.apply_reflect_padding#1",
      "cstart": 49,
      "cend": 49,
      "tstart": 414,
      "tend": 414
    },
    {
      "id": 420,
      "name": "step 420",
      "method": "src.test_reflect.apply_reflect_padding#1",
      "cstart": 44,
      "cend": 44,
      "tstart": 415,
      "tend": 415
    },
    {
      "id": 421,
      "name": "step 421",
      "method": "src.test_reflect.apply_reflect_padding#1",
      "cstart": 45,
      "cend": 45,
      "tstart": 416,
      "tend": 416
    },
    {
      "id": 422,
      "name": "step 422",
      "method": "src.test_reflect.apply_reflect_padding#1",
      "cstart": 46,
      "cend": 46,
      "tstart": 417,
      "tend": 417
    },
    {
      "id": 423,
      "name": "step 423",
      "method": "src.test_reflect.apply_reflect_padding#1",
      "cstart": 49,
      "cend": 49,
      "tstart": 418,
      "tend": 418
    },
    {
      "id": 424,
      "name": "step 424",
      "method": "src.test_reflect.apply_reflect_padding#1",
      "cstart": 44,
      "cend": 44,
      "tstart": 419,
      "tend": 419
    },
    {
      "id": 425,
      "name": "step 425",
      "method": "src.test_reflect.apply_reflect_padding#1",
      "cstart": 43,
      "cend": 43,
      "tstart": 420,
      "tend": 420
    },
    {
      "id": 426,
      "name": "step 426",
      "method": "src.test_reflect.apply_reflect_padding#1",
      "cstart": 51,
      "cend": 51,
      "tstart": 421,
      "tend": 421
    },
    {
      "id": 427,
      "name": "step 427",
      "method": "src.test_reflect.apply_reflect_padding#1",
      "cstart": 51,
      "cend": 51,
      "tstart": -1,
      "tend": -1
    },
    {
      "id": 428,
      "name": "step 428",
      "method": "src.test_reflect.apply_reflect_padding#1",
      "cstart": 62,
      "cend": 62,
      "tstart": 424,
      "tend": 424
    },
    {
      "id": 429,
      "name": "step 429",
      "method": "src.test_reflect.apply_reflect_padding#1",
      "cstart": 63,
      "cend": 63,
      "tstart": 425,
      "tend": 425
    },
    {
      "id": 430,
      "name": "step 430",
      "method": "src.test_reflect.apply_reflect_padding#1",
      "cstart": 62,
      "cend": 62,
      "tstart": 426,
      "tend": 426
    },
    {
      "id": 431,
      "name": "step 431",
      "method": "src.test_reflect.apply_reflect_padding#1",
      "cstart": 63,
      "cend": 63,
      "tstart": 427,
      "tend": 427
    },
    {
      "id": 432,
      "name": "step 432",
      "method": "src.test_reflect.apply_reflect_padding#1",
      "cstart": 62,
      "cend": 62,
      "tstart": 428,
      "tend": 428
    },
    {
      "id": 433,
      "name": "step 433",
      "method": "src.test_reflect.apply_reflect_padding#1",
      "cstart": 63,
      "cend": 63,
      "tstart": 429,
      "tend": 429
    },
    {
      "id": 434,
      "name": "step 434",
      "method": "src.test_reflect.apply_reflect_padding#1",
      "cstart": 62,
      "cend": 62,
      "tstart": 430,
      "tend": 430
    },
    {
      "id": 435,
      "name": "step 435",
      "method": "src.test_reflect.apply_reflect_padding#1",
      "cstart": 63,
      "cend": 63,
      "tstart": 431,
      "tend": 431
    },
    {
      "id": 436,
      "name": "step 436",
      "method": "src.test_reflect.apply_reflect_padding#1",
      "cstart": 62,
      "cend": 62,
      "tstart": 432,
      "tend": 432
    },
    {
      "id": 437,
      "name": "step 437",
      "method": "src.test_reflect.apply_reflect_padding#1",
      "cstart": 63,
      "cend": 63,
      "tstart": 433,
      "tend": 433
    },
    {
      "id": 438,
      "name": "step 438",
      "method": "src.test_reflect.apply_reflect_padding#1",
      "cstart": 62,
      "cend": 62,
      "tstart": 434,
      "tend": 434
    },
    {
      "id": 439,
      "name": "step 439",
      "method": "src.test_reflect.apply_reflect_padding#1",
      "cstart": 63,
      "cend": 63,
      "tstart": 435,
      "tend": 435
    },
    {
      "id": 440,
      "name": "step 440",
      "method": "src.test_reflect.apply_reflect_padding#1",
      "cstart": 62,
      "cend": 62,
      "tstart": 436,
      "tend": 436
    },
    {
      "id": 441,
      "name": "step 441",
      "method": "src.test_reflect.apply_reflect_padding#1",
      "cstart": 63,
      "cend": 63,
      "tstart": 437,
      "tend": 437
    },
    {
      "id": 442,
      "name": "step 442",
      "method": "src.test_reflect.apply_reflect_padding#1",
      "cstart": 62,
      "cend": 62,
      "tstart": 438,
      "tend": 438
    },
    {
      "id": 443,
      "name": "step 443",
      "method": "src.test_reflect.apply_reflect_padding#1",
      "cstart": 65,
      "cend": 65,
      "tstart": 439,
      "tend": 439
    },
    {
      "id": 444,
      "name": "step 444",
      "method": "src.test_reflect.apply_reflect_padding#1",
      "cstart": 66,
      "cend": 66,
      "tstart": 440,
      "tend": 440
    },
    {
      "id": 445,
      "name": "step 445",
      "method": "src.test_reflect.apply_reflect_padding#1",
      "cstart": 67,
      "cend": 67,
      "tstart": 441,
      "tend": 441
    },
    {
      "id": 446,
      "name": "step 446",
      "method": "src.test_reflect.apply_reflect_padding#1",
      "cstart": 67,
      "cend": 67,
      "tstart": 442,
      "tend": 442
    },
    {
      "id": 447,
      "name": "step 447",
      "method": "src.test_reflect.apply_reflect_padding#1",
      "cstart": 67,
      "cend": 67,
      "tstart": 443,
      "tend": 443
    },
    {
      "id": 448,
      "name": "step 448",
      "method": "src.test_reflect.apply_reflect_padding#1",
      "cstart": 67,
      "cend": 67,
      "tstart": 444,
      "tend": 444
    },
    {
      "id": 449,
      "name": "step 449",
      "method": "src.test_reflect.apply_reflect_padding#1",
      "cstart": 67,
      "cend": 67,
      "tstart": 445,
      "tend": 445
    },
    {
      "id": 450,
      "name": "step 450",
      "method": "src.test_reflect.apply_reflect_padding#1",
      "cstart": 67,
      "cend": 67,
      "tstart": 446,
      "tend": 446
    },
    {
      "id": 451,
      "name": "step 451",
      "method": "src.test_reflect.apply_reflect_padding#1",
      "cstart": 67,
      "cend": 67,
      "tstart": 447,
      "tend": 447
    },
    {
      "id": 452,
      "name": "step 452",
      "method": "src.test_reflect.apply_reflect_padding#1",
      "cstart": 69,
      "cend": 69,
      "tstart": 449,
      "tend": 449
    },
    {
      "id": 453,
      "name": "step 453",
      "method": "src.test_reflect.apply_reflect_padding#1",
      "cstart": 69,
      "cend": 69,
      "tstart": 450,
      "tend": 450
    },
    {
      "id": 454,
      "name": "step 454",
      "method": "src.test_reflect.apply_reflect_padding#1",
      "cstart": 69,
      "cend": 69,
      "tstart": -1,
      "tend": -1
    }
  ]
}
